MANIFEST.in
README.rst
setup.cfg
setup.py
sentry_hipchat/__init__.py
sentry_hipchat/models.py
sentry_hipchat.egg-info/PKG-INFO
sentry_hipchat.egg-info/SOURCES.txt
sentry_hipchat.egg-info/dependency_links.txt
sentry_hipchat.egg-info/entry_points.txt
sentry_hipchat.egg-info/not-zip-safe
sentry_hipchat.egg-info/pbr.json
sentry_hipchat.egg-info/requires.txt
sentry_hipchat.egg-info/top_level.txt