Metadata-Version: 1.1
Name: sentry-hipchat
Version: 0.6.0
Summary: A Sentry extension which integrates with Hipchat.
Home-page: http://github.com/linovia/sentry-hipchat
Author: Xavier Ordoquy
Author-email: xordoquy@linovia.com
License: BSD
Platform: UNKNOWN
Classifier: Framework :: Django
Classifier: Intended Audience :: Developers
Classifier: Intended Audience :: System Administrators
Classifier: Operating System :: OS Independent
Classifier: Topic :: Software Development
